ffcclient/__init__.py
ffcclient/category.py
ffcclient/client.py
ffcclient/common_types.py
ffcclient/config.py
ffcclient/data_storage.py
ffcclient/evaluator.py
ffcclient/event_processor.py
ffcclient/event_types.py
ffcclient/interfaces.py
ffcclient/status.py
ffcclient/status_types.py
ffcclient/streaming.py
ffcclient/update_processor.py
ffcclient/version.py
ffcclient/utils/__init__.py
ffcclient/utils/exceptions.py
ffcclient/utils/exponential_backoff_jitter_strategy.py
ffcclient/utils/http_client.py
ffcclient/utils/repeatable_task.py
ffcclient/utils/rwlock.py
ffcclient/utils/variation_splitting_algorithm.py
ffc_server_python_sdk-1.1.0.dist-info/LICENSE
ffc_server_python_sdk-1.1.0.dist-info/METADATA
ffc_server_python_sdk-1.1.0.dist-info/WHEEL
ffc_server_python_sdk-1.1.0.dist-info/top_level.txt
ffc_server_python_sdk-1.1.0.dist-info/RECORD
