Metadata-Version: 2.1
Name: ffc-server-python-sdk
Version: 1.1.0
Summary: A Python Server SDK for featureflag.co project
Home-page: https://github.com/feature-flags-co/ffc-server-python-sdk
Author: Dian SUN
Author-email: dian.sun0720@gmail.com
Project-URL: Code, https://github.com/feature-flags-co/ffc-server-python-sdk
Project-URL: Issue tracker, https://github.com/feature-flags-co/ffc-server-python-sdk/issues
Classifier: Development Status :: 4 - Beta
Classifier: Intended Audience :: Developers
Classifier: License :: OSI Approved :: Apache Software License
Classifier: Operating System :: OS Independent
Classifier: Topic :: Software Development
Classifier: Topic :: Software Development :: Libraries
Classifier: Programming Language :: Python :: 3.6
Classifier: Programming Language :: Python :: 3.7
Classifier: Programming Language :: Python :: 3.8
Classifier: Programming Language :: Python :: 3.9
Requires-Python: >=3.6, <=3.9
License-File: LICENSE
Requires-Dist: certifi (>=2018.4.16)
Requires-Dist: urllib3 (>=1.22.0)
Requires-Dist: schedule (>=1.0.0)
Requires-Dist: websocket-client (>=1.0.0)
Requires-Dist: atomics (>=1.0.2)
Provides-Extra: dev
Requires-Dist: certifi (>=2018.4.16) ; extra == 'dev'
Requires-Dist: urllib3 (>=1.22.0) ; extra == 'dev'
Requires-Dist: schedule (>=1.0.0) ; extra == 'dev'
Requires-Dist: websocket-client (>=1.0.0) ; extra == 'dev'
Requires-Dist: atomics (>=1.0.2) ; extra == 'dev'
Requires-Dist: flake8 ; extra == 'dev'
Requires-Dist: pytest ; extra == 'dev'
Requires-Dist: autopep8 ; extra == 'dev'
Requires-Dist: build ; extra == 'dev'
Requires-Dist: twine ; extra == 'dev'
